{
  "_fv": 24,
  "_type": "livingentity",
  "definition": {
    "mobName": "Sneaker",
    "mobLabel": "",
    "mobModelName": "Creeper",
    "mobModelTexture": "creeper_end.png",
    "mobModelGlowTexture": "",
    "modelWidth": 0.6,
    "modelHeight": 1.7,
    "modelShadowSize": 0.5,
    "mountedYOffset": 0.0,
    "hasSpawnEgg": true,
    "spawnEggBaseColor": {
      "value": -6750055,
      "falpha": 0.0
    },
    "spawnEggDotColor": {
      "value": -65281,
      "falpha": 0.0
    },
    "creativeTab": {
      "value": "CUSTOM:Betterendstuff"
    },
    "isBoss": false,
    "bossBarColor": "PINK",
    "bossBarType": "PROGRESS",
    "equipmentMainHand": {
      "value": ""
    },
    "equipmentOffHand": {
      "value": ""
    },
    "equipmentHelmet": {
      "value": ""
    },
    "equipmentBody": {
      "value": ""
    },
    "equipmentLeggings": {
      "value": ""
    },
    "equipmentBoots": {
      "value": ""
    },
    "mobBehaviourType": "Mob",
    "mobCreatureType": "UNDEFINED",
    "attackStrength": 15,
    "attackKnockback": 1.0,
    "knockbackResistance": 0.0,
    "movementSpeed": 0.3,
    "armorBaseValue": 3.0,
    "trackingRange": 64,
    "health": 50,
    "xpAmount": 10,
    "waterMob": false,
    "flyingMob": false,
    "guiBoundTo": "<NONE>",
    "inventorySize": 9,
    "inventoryStackSize": 64,
    "disableCollisions": false,
    "ridable": false,
    "canControlForward": false,
    "canControlStrafe": false,
    "immuneToFire": false,
    "immuneToArrows": false,
    "immuneToFallDamage": false,
    "immuneToCactus": false,
    "immuneToDrowning": false,
    "immuneToLightning": false,
    "immuneToPotions": false,
    "immuneToPlayer": false,
    "immuneToExplosion": false,
    "immuneToTrident": false,
    "immuneToAnvil": false,
    "immuneToWither": false,
    "immuneToDragonBreath": false,
    "mobDrop": {
      "value": "CUSTOM:Dragoncharge"
    },
    "livingSound": {
      "value": ""
    },
    "hurtSound": {
      "value": "entity.endermen.hurt"
    },
    "deathSound": {
      "value": "entity.enderdragon_fireball.explode"
    },
    "stepSound": {
      "value": ""
    },
    "spawnParticles": false,
    "particleToSpawn": {
      "value": "CUSTOM:Endsandparticle"
    },
    "particleSpawningShape": "Spread",
    "particleSpawningRadious": 0.5,
    "particleAmount": 4,
    "hasAI": true,
    "aiBase": "Creeper",
    "aixml": "<xml xmlns=\"https://developers.google.com/blockly/xml\"><block type=\"aitasks_container\" deletable=\"false\" x=\"40\" y=\"40\"><next><block type=\"look_around\"><field name=\"condition\">null,null</field><next><block type=\"attack_on_collide\"><field name=\"speed\">1.2</field><field name=\"longmemory\">FALSE</field><field name=\"condition\">null,null</field><next><block type=\"attack_action\"><field name=\"callhelp\">FALSE</field><field name=\"condition\">null,null</field><next><block type=\"wander\"><field name=\"speed\">1</field><field name=\"condition\">null,null</field></block></next></block></next></block></next></block></next></block></xml>",
    "breedable": false,
    "tameable": false,
    "breedTriggerItems": [],
    "ranged": false,
    "rangedAttackItem": {
      "value": ""
    },
    "rangedItemType": "Default item",
    "spawnThisMob": true,
    "doesDespawnWhenIdle": true,
    "spawningCondition": {
      "name": "SneakerNaturalEntitySpawningCondition"
    },
    "spawningProbability": 7,
    "mobSpawningType": "monster",
    "minNumberOfMobsPerGroup": 4,
    "maxNumberOfMobsPerGroup": 4,
    "restrictionBiomes": [
      {
        "value": "CUSTOM:Dragon"
      },
      {
        "value": "CUSTOM:Enddesert"
      },
      {
        "value": "CUSTOM:Enderdesertsplit"
      },
      {
        "value": "CUSTOM:Enderforest"
      },
      {
        "value": "CUSTOM:Enderhills"
      },
      {
        "value": "CUSTOM:Magicforest"
      },
      {
        "value": "CUSTOM:Obsidantowers"
      },
      {
        "value": "CUSTOM:Sun"
      },
      {
        "value": "CUSTOM:Water"
      },
      {
        "value": "CUSTOM:Youngdragonforest"
      },
      {
        "value": "CUSTOM:Youngenderforest"
      },
      {
        "value": "CUSTOM:Youngmagicforest"
      },
      {
        "value": "CUSTOM:Youngsunforest"
      },
      {
        "value": "CUSTOM:Youngwaterforest"
      }
    ],
    "spawnInDungeons": false
  }
}